portalbrasil/__init__.py
portalbrasil/core/__init__.py
portalbrasil/core/_types.py
portalbrasil/core/configure.zcml
portalbrasil/core/dependencies.zcml
portalbrasil/core/factory.py
portalbrasil/core/interfaces.py
portalbrasil/core/permissions.zcml
portalbrasil/core/profiles.zcml
portalbrasil/core/behaviors/__init__.py
portalbrasil/core/behaviors/configure.zcml
portalbrasil/core/behaviors/footer.py
portalbrasil/core/behaviors/header.py
portalbrasil/core/behaviors/networks.py
portalbrasil/core/content/__init__.py
portalbrasil/core/controlpanel/__init__.py
portalbrasil/core/controlpanel/configure.zcml
portalbrasil/core/indexers/__init__.py
portalbrasil/core/indexers/configure.zcml
portalbrasil/core/locales/__init__.py
portalbrasil/core/locales/__main__.py
portalbrasil/core/locales/portalbrasil.core.pot
portalbrasil/core/locales/en/LC_MESSAGES/portalbrasil.core.mo
portalbrasil/core/locales/en/LC_MESSAGES/portalbrasil.core.po
portalbrasil/core/locales/pt_BR/LC_MESSAGES/portalbrasil.core.mo
portalbrasil/core/locales/pt_BR/LC_MESSAGES/portalbrasil.core.po
portalbrasil/core/profiles/base/actions.xml
portalbrasil/core/profiles/base/browserlayer.xml
portalbrasil/core/profiles/base/catalog.xml
portalbrasil/core/profiles/base/componentregistry.xml
portalbrasil/core/profiles/base/contenttyperegistry.xml
portalbrasil/core/profiles/base/controlpanel.xml
portalbrasil/core/profiles/base/mailhost.xml
portalbrasil/core/profiles/base/memberdata_properties.xml
portalbrasil/core/profiles/base/metadata.xml
portalbrasil/core/profiles/base/properties.xml
portalbrasil/core/profiles/base/rolemap.xml
portalbrasil/core/profiles/base/skins.xml
portalbrasil/core/profiles/base/toolset.xml
portalbrasil/core/profiles/base/types.xml
portalbrasil/core/profiles/base/viewlets.xml
portalbrasil/core/profiles/base/workflows.xml
portalbrasil/core/profiles/base/types/Plone_Site.xml
portalbrasil/core/profiles/base/types/TempFolder.xml
portalbrasil_core-1.0.0a8.dist-info/METADATA
portalbrasil_core-1.0.0a8.dist-info/WHEEL
portalbrasil_core-1.0.0a8.dist-info/entry_points.txt
portalbrasil_core-1.0.0a8.dist-info/licenses/LICENSE.GPL
portalbrasil_core-1.0.0a8.dist-info/licenses/LICENSE.md
portalbrasil_core-1.0.0a8.dist-info/RECORD
